hing_p/__init__.py
hing_p/course.py
hing_p/student.py
hing_p-0.1.dist-info/LICENSE
hing_p-0.1.dist-info/METADATA
hing_p-0.1.dist-info/WHEEL
hing_p-0.1.dist-info/top_level.txt
hing_p-0.1.dist-info/RECORD
