Metadata-Version: 2.1
Name: hing-p
Version: 0.1
Summary: A package for managing school courses and students
Author: yongjin
Author-email: kimyongjin0305@gmail.com
Classifier: Programming Language :: Python :: 3
Classifier: License :: OSI Approved :: MIT License
Classifier: Operating System :: OS Independent
Requires-Python: >=3.6
License-File: LICENSE
